{
  "kind": "collectionType",
  "collectionName": "services",
  "info": {
    "name": "Service"
  },
  "options": {
    "increments": true,
    "timestamps": true,
    "draftAndPublish": true
  },
  "pluginOptions": {},
  "attributes": {
    "Title": {
      "type": "string",
      "required": true,
      "unique": true
    },
    "Description": {
      "type": "text",
      "required": true,
      "unique": true
    },
    "Image": {
      "model": "file",
      "via": "related",
      "allowedTypes": [
        "images",
        "files",
        "videos"
      ],
      "plugin": "upload",
      "required": false,
      "pluginOptions": {}
    }
  }
}
